dictalchemy/__init__.py
dictalchemy/classes.py
dictalchemy/constants.py
dictalchemy/errors.py
dictalchemy/utils.py
dictalchemy/tests/__init__.py
dictalchemy/tests/test_asdict.py
dictalchemy/tests/test_fromdict.py
dictalchemy/tests/test_utils.py
zmdictalchemy/__init__.py
zmdictalchemy/classes.py
zmdictalchemy/constants.py
zmdictalchemy/errors.py
zmdictalchemy/utils.py
zmdictalchemy/tests/__init__.py
zmdictalchemy/tests/test_asdict.py
zmdictalchemy/tests/test_fromdict.py
zmdictalchemy/tests/test_utils.py
zmdictalchemy-0.1.2.9.dist-info/LICENSE
zmdictalchemy-0.1.2.9.dist-info/METADATA
zmdictalchemy-0.1.2.9.dist-info/WHEEL
zmdictalchemy-0.1.2.9.dist-info/top_level.txt
zmdictalchemy-0.1.2.9.dist-info/RECORD
